[{"name":"metadata.json","path":"dist/metadata.json","internal_type":30,"type":"Metadata"},{"name":"aurora","path":"dist/aurora_freebsd_arm64/aurora","goos":"freebsd","goarch":"arm64","internal_type":4,"type":"Binary","extra":{"Binary":"aurora","Ext":"","ID":"aurora"}},{"name":"aurora","path":"dist/aurora_darwin_amd64_v1/aurora","goos":"darwin","goarch":"amd64","goamd64":"v1","internal_type":4,"type":"Binary","extra":{"Binary":"aurora","Ext":"","ID":"aurora"}},{"name":"aurora","path":"dist/aurora_linux_arm64/aurora","goos":"linux","goarch":"arm64","internal_type":4,"type":"Binary","extra":{"Binary":"aurora","Ext":"","ID":"aurora"}},{"name":"aurora","path":"dist/aurora_linux_amd64_v1/aurora","goos":"linux","goarch":"amd64","goamd64":"v1","internal_type":4,"type":"Binary","extra":{"Binary":"aurora","Ext":"","ID":"aurora"}},{"name":"aurora","path":"dist/aurora_linux_arm_6/aurora","goos":"linux","goarch":"arm","goarm":"6","internal_type":4,"type":"Binary","extra":{"Binary":"aurora","Ext":"","ID":"aurora"}},{"name":"aurora.exe","path":"dist/aurora_windows_arm64/aurora.exe","goos":"windows","goarch":"arm64","internal_type":4,"type":"Binary","extra":{"Binary":"aurora","Ext":".exe","ID":"aurora"}},{"name":"aurora","path":"dist/aurora_freebsd_amd64_v1/aurora","goos":"freebsd","goarch":"amd64","goamd64":"v1","internal_type":4,"type":"Binary","extra":{"Binary":"aurora","Ext":"","ID":"aurora"}},{"name":"aurora","path":"dist/aurora_darwin_arm64/aurora","goos":"darwin","goarch":"arm64","internal_type":4,"type":"Binary","extra":{"Binary":"aurora","Ext":"","ID":"aurora"}},{"name":"aurora","path":"dist/aurora_linux_arm_7/aurora","goos":"linux","goarch":"arm","goarm":"7","internal_type":4,"type":"Binary","extra":{"Binary":"aurora","Ext":"","ID":"aurora"}},{"name":"aurora.exe","path":"dist/aurora_windows_amd64_v1/aurora.exe","goos":"windows","goarch":"amd64","goamd64":"v1","internal_type":4,"type":"Binary","extra":{"Binary":"aurora","Ext":".exe","ID":"aurora"}},{"name":"auroraboreas-v1.0.0-next-linux-armv6.tar.gz","path":"dist/auroraboreas-v1.0.0-next-linux-armv6.tar.gz","goos":"linux","goarch":"arm","goarm":"6","internal_type":1,"type":"Archive","extra":{"Binaries":["aurora"],"Checksum":"sha256:cfad4abe1b964d46804a24270c842e223678208dbfad889574198ad0fbad5646","Format":"tar.gz","ID":"aurora-archive","Replaces":null,"WrappedIn":"auroraboreas-v1.0.0-next-linux-armv6"}},{"name":"auroraboreas-v1.0.0-next-darwin-amd64.tar.gz","path":"dist/auroraboreas-v1.0.0-next-darwin-amd64.tar.gz","goos":"darwin","goarch":"amd64","goamd64":"v1","internal_type":1,"type":"Archive","extra":{"Binaries":["aurora"],"Checksum":"sha256:435d4a89d48af9b8c258e76d153d16fcc2aea1eac69d419e078eb0076b7f0a3a","Format":"tar.gz","ID":"aurora-archive","Replaces":null,"WrappedIn":"auroraboreas-v1.0.0-next-darwin-amd64"}},{"name":"auroraboreas-v1.0.0-next-linux-arm64.tar.gz","path":"dist/auroraboreas-v1.0.0-next-linux-arm64.tar.gz","goos":"linux","goarch":"arm64","internal_type":1,"type":"Archive","extra":{"Binaries":["aurora"],"Checksum":"sha256:1d5d0bb7f722994b0f7dc072fbf16e963f9ad608eabe583e85d81ed3f1a15cc9","Format":"tar.gz","ID":"aurora-archive","Replaces":null,"WrappedIn":"auroraboreas-v1.0.0-next-linux-arm64"}},{"name":"auroraboreas-v1.0.0-next-linux-amd64.tar.gz","path":"dist/auroraboreas-v1.0.0-next-linux-amd64.tar.gz","goos":"linux","goarch":"amd64","goamd64":"v1","internal_type":1,"type":"Archive","extra":{"Binaries":["aurora"],"Checksum":"sha256:d1461c67a2812ba61cfcb427d5f49409ebd2fbf4fc2d7458c919d91968b865d8","Format":"tar.gz","ID":"aurora-archive","Replaces":null,"WrappedIn":"auroraboreas-v1.0.0-next-linux-amd64"}},{"name":"auroraboreas-v1.0.0-next-windows-arm64.zip","path":"dist/auroraboreas-v1.0.0-next-windows-arm64.zip","goos":"windows","goarch":"arm64","internal_type":1,"type":"Archive","extra":{"Binaries":["aurora.exe"],"Checksum":"sha256:1fa68e9d0ba06d9206eaae222372fe4e2215ac0d617832d0c9dda44539826606","Format":"zip","ID":"aurora-archive","Replaces":null,"WrappedIn":"auroraboreas-v1.0.0-next-windows-arm64"}},{"name":"auroraboreas-v1.0.0-next-freebsd-amd64.tar.gz","path":"dist/auroraboreas-v1.0.0-next-freebsd-amd64.tar.gz","goos":"freebsd","goarch":"amd64","goamd64":"v1","internal_type":1,"type":"Archive","extra":{"Binaries":["aurora"],"Checksum":"sha256:e500da53ffd7a1a519a5f0cc3fbb2344046843fbbfc71404eccbc2a7726d6a2d","Format":"tar.gz","ID":"aurora-archive","Replaces":null,"WrappedIn":"auroraboreas-v1.0.0-next-freebsd-amd64"}},{"name":"auroraboreas-v1.0.0-next-darwin-arm64.tar.gz","path":"dist/auroraboreas-v1.0.0-next-darwin-arm64.tar.gz","goos":"darwin","goarch":"arm64","internal_type":1,"type":"Archive","extra":{"Binaries":["aurora"],"Checksum":"sha256:7507c4de89bf353624a4b36ba246a9bb3bf270a2000b07e2010d4ad7a4dffdc5","Format":"tar.gz","ID":"aurora-archive","Replaces":null,"WrappedIn":"auroraboreas-v1.0.0-next-darwin-arm64"}},{"name":"auroraboreas-v1.0.0-next-linux-armv7.tar.gz","path":"dist/auroraboreas-v1.0.0-next-linux-armv7.tar.gz","goos":"linux","goarch":"arm","goarm":"7","internal_type":1,"type":"Archive","extra":{"Binaries":["aurora"],"Checksum":"sha256:335f4e3bbe226108c492a7124fad3de5b49d70740675ef960d6783747657789a","Format":"tar.gz","ID":"aurora-archive","Replaces":null,"WrappedIn":"auroraboreas-v1.0.0-next-linux-armv7"}},{"name":"auroraboreas-v1.0.0-next-freebsd-arm64.tar.gz","path":"dist/auroraboreas-v1.0.0-next-freebsd-arm64.tar.gz","goos":"freebsd","goarch":"arm64","internal_type":1,"type":"Archive","extra":{"Binaries":["aurora"],"Checksum":"sha256:8bf2c89c14aa35963082758b3aca258df8fa736e7ac228270cb41aab47885f06","Format":"tar.gz","ID":"aurora-archive","Replaces":null,"WrappedIn":"auroraboreas-v1.0.0-next-freebsd-arm64"}},{"name":"auroraboreas-v1.0.0-next-windows-amd64.zip","path":"dist/auroraboreas-v1.0.0-next-windows-amd64.zip","goos":"windows","goarch":"amd64","goamd64":"v1","internal_type":1,"type":"Archive","extra":{"Binaries":["aurora.exe"],"Checksum":"sha256:ac078118b01579c565162a0502b19e1709f7eb46e6306f96dfc2bd175034d6aa","Format":"zip","ID":"aurora-archive","Replaces":null,"WrappedIn":"auroraboreas-v1.0.0-next-windows-amd64"}},{"name":"checksums.txt","path":"dist/checksums.txt","internal_type":12,"type":"Checksum","extra":{}},{"name":"auroraboreas.rb","path":"dist/homebrew/auroraboreas.rb","internal_type":16,"type":"Brew Tap","extra":{"BrewConfig":{"name":"auroraboreas","repository":{"owner":"nataliagranato","name":"homebrew-tap","branch":"main","git":{},"pull_request":{"base":{}}},"commit_author":{"name":"Natalia Granato","email":"contato@nataliagranato.xyz"},"commit_msg_template":"Brew formula update for {{ .ProjectName }} version {{ .Tag }}","install":"bin.install \"aurora\"\n","test":"system \"#{bin}/aurora\", \"--version\"\n","description":"Aurora Boreas - Poesia e visualização de céu estrelado","homepage":"https://github.com/nataliagranato/auroraboreas","license":"GPL-3.0","goarm":"6","goamd64":"v1","tap":{"git":{},"pull_request":{"base":{}}}}}},{"name":"nataliagranato/auroraboreas:v1.0.0-next","path":"nataliagranato/auroraboreas:v1.0.0-next","goos":"linux","goarch":"amd64","goarm":"6","internal_type":9,"type":"Docker Image","extra":{"DockerConfig":{"goos":"linux","goarch":"amd64","goarm":"6","goamd64":"v1","dockerfile":"Dockerfile","image_templates":["nataliagranato/auroraboreas:{{ .Version }}","nataliagranato/auroraboreas:latest"],"use":"docker"}}},{"name":"nataliagranato/auroraboreas:latest","path":"nataliagranato/auroraboreas:latest","goos":"linux","goarch":"amd64","goarm":"6","internal_type":9,"type":"Docker Image","extra":{"DockerConfig":{"goos":"linux","goarch":"amd64","goarm":"6","goamd64":"v1","dockerfile":"Dockerfile","image_templates":["nataliagranato/auroraboreas:{{ .Version }}","nataliagranato/auroraboreas:latest"],"use":"docker"}}}]